graph_orchestrator-0.2.5.dist-info/licenses/LICENSE
graphorchestrator/__init__.py
graphorchestrator/ai/__init__.py
graphorchestrator/ai/ai_action.py
graphorchestrator/core/__init__.py
graphorchestrator/core/checkpoint.py
graphorchestrator/core/exceptions.py
graphorchestrator/core/log_constants.py
graphorchestrator/core/log_context.py
graphorchestrator/core/log_utils.py
graphorchestrator/core/logger.py
graphorchestrator/core/retry.py
graphorchestrator/core/state.py
graphorchestrator/decorators/__init__.py
graphorchestrator/decorators/actions.py
graphorchestrator/decorators/builtin_actions.py
graphorchestrator/edges/__init__.py
graphorchestrator/edges/base.py
graphorchestrator/edges/concrete.py
graphorchestrator/edges/conditional.py
graphorchestrator/graph/__init__.py
graphorchestrator/graph/builder.py
graphorchestrator/graph/executor.py
graphorchestrator/graph/graph.py
graphorchestrator/nodes/__init__.py
graphorchestrator/nodes/base.py
graphorchestrator/nodes/nodes.py
graphorchestrator/toolsetserver/__init__.py
graphorchestrator/toolsetserver/__main__.py
graphorchestrator/toolsetserver/runtime.py
graphorchestrator/visualization/__init__.py
graphorchestrator/visualization/representation.py
graphorchestrator/visualization/visualizer.py
tests/__init__.py
tests/test_checkpoint.py
tests/test_graph.py
tests/test_toolsetserver.py
tests/test_toolsetservercli.py
tests/test_visualization.py
graph_orchestrator-0.2.5.dist-info/METADATA
graph_orchestrator-0.2.5.dist-info/WHEEL
graph_orchestrator-0.2.5.dist-info/entry_points.txt
graph_orchestrator-0.2.5.dist-info/top_level.txt
graph_orchestrator-0.2.5.dist-info/RECORD
